{"11": {"Sujet": ["Environnement:", "Environnement: Changements climatiques - adaptation", "Environnement: Changements climatiques \u2013 att\u00e9nuation", "Environnement: L\u2019\u00e9cotransport", "Environnement: D\u00e9chets", "Environnement: D\u00e9chets: Recyclage", "Environnement: D\u00e9chets: R\u00e9duction", "Environnement: D\u00e9chets: R\u00e9utillisation", "Environnement: Valorisation de l'eau"], "Resource type": ["Case Study"], "Endroit": ["Canada", "\u00c9tats-Unis"], "Outils de changement utilis\u00e9s": ["Soutenir la motivation au fil du temps", "Attrait des normes"], "Landmark designation?": ["Non"], "Afficher seulement les \u00e9tudes de cas des programmes qui font l'objet d'une diffusion g\u00e9n\u00e9rale": ["Oui"]}, "21": {"Sujet": ["Environnement:", "Environnement: D\u00e9chets", "Environnement: D\u00e9chets: D\u00e9chets domestiques dangereux", "Environnement: D\u00e9chets: Recyclage", "Environnement: D\u00e9chets: R\u00e9utillisation"], "Resource type": ["Case Study"], "Endroit": ["Canada", "Canada-Ontario"], "Outils de changement utilis\u00e9s": ["M\u00e9dias", "Attrait des normes"], "Landmark designation?": ["Non"], "Afficher seulement les \u00e9tudes de cas des programmes qui font l'objet d'une diffusion g\u00e9n\u00e9rale": ["Non"]}, "22": {"Sujet": ["Environnement:", "Environnement: Changements climatiques \u2013 att\u00e9nuation", "Environnement: Efficacit\u00e9 \u00e9nerg\u00e9tique", "Environnement: Valorisation de l'eau"], "Resource type": ["Case Study"], "Endroit": ["Canada", "Canada-Nouvelle-\u00c9cosse"], "Outils de changement utilis\u00e9s": ["Communications personnalis\u00e9es percutantes", "Soutenir la motivation au fil du temps", "Attrait des normes"], "Landmark designation?": ["Non"], "Afficher seulement les \u00e9tudes de cas des programmes qui font l'objet d'une diffusion g\u00e9n\u00e9rale": ["Oui"]}, "60": {"Sujet": ["Environnement:", "Environnement: Changements climatiques \u2013 att\u00e9nuation", "Environnement: L\u2019\u00e9cotransport", "Promotion de la sant\u00e9", "Promotion de la sant\u00e9: Vie active", "Promotion de la sant\u00e9: Sant\u00e9 cardiovasculaire"], "Resource type": ["Case Study"], "Endroit": ["Canada", "Canada-British Columbia"], "Outils de changement utilis\u00e9s": ["Communications personnalis\u00e9es percutantes", "Soutenir la motivation au fil du temps", "Attrait des normes"], "Landmark designation?": ["Non"], "Afficher seulement les \u00e9tudes de cas des programmes qui font l'objet d'une diffusion g\u00e9n\u00e9rale": ["Non"]}, "446": {"Sujet": ["Environnement:", "Environnement: L\u2019\u00e9cotransport"], "Resource type": ["Case Study"], "Endroit": ["Canada-Quebec"], "Landmark designation?": ["Oui"], "Afficher seulement les \u00e9tudes de cas des programmes qui font l'objet d'une diffusion g\u00e9n\u00e9rale": ["Non"]}, "91": {"Sujet": ["Environnement:", "Environnement: Changements climatiques \u2013 att\u00e9nuation", "Environnement: Efficacit\u00e9 \u00e9nerg\u00e9tique", "Environnement: L\u2019\u00e9cotransport", "Promotion de la sant\u00e9: Conditions du milieu"], "Resource type": ["Case Study"], "Endroit": ["\u00c9tats-Unis", "EU-Oregon"], "Outils de changement utilis\u00e9s": ["M\u00e9dias", "Communications personnalis\u00e9es percutantes", "Soutenir la motivation au fil du temps"], "Landmark designation?": ["Non"], "Afficher seulement les \u00e9tudes de cas des programmes qui font l'objet d'une diffusion g\u00e9n\u00e9rale": ["Non"]}, "95": {"Sujet": ["Environnement:", "Environnement: Changements climatiques \u2013 att\u00e9nuation", "Environnement: L\u2019\u00e9cotransport", "Promotion de la sant\u00e9", "Promotion de la sant\u00e9: Vie active", "Promotion de la sant\u00e9: Sant\u00e9 cardiovasculaire"], "Resource type": ["Case Study"], "Endroit": ["Canada", "Canada-British Columbia"], "Outils de changement utilis\u00e9s": ["M\u00e9dias", "Communications personnalis\u00e9es percutantes"], "Landmark designation?": ["Non"], "Afficher seulement les \u00e9tudes de cas des programmes qui font l'objet d'une diffusion g\u00e9n\u00e9rale": ["Oui"]}, "96": {"Sujet": ["Environnement:", "Environnement: Air pur", "Environnement: Changements climatiques \u2013 att\u00e9nuation", "Environnement: L\u2019\u00e9cotransport"], "Resource type": ["Case Study"], "Endroit": ["\u00c9tats-Unis", "EU-Washington"], "Outils de changement utilis\u00e9s": ["M\u00e9dias", "Attrait des normes"], "Landmark designation?": ["Non"], "Afficher seulement les \u00e9tudes de cas des programmes qui font l'objet d'une diffusion g\u00e9n\u00e9rale": ["Non"]}, "97": {"Sujet": ["Environnement:", "Environnement: Air pur", "Environnement: L\u2019\u00e9cotransport", "Promotion de la sant\u00e9", "Promotion de la sant\u00e9: Vie active", "Promotion de la sant\u00e9: Sant\u00e9 cardiovasculaire"], "Resource type": ["Case Study"], "Endroit": ["Canada", "Canada-Ontario"], "Outils de changement utilis\u00e9s": ["M\u00e9dias", "Soutenir la motivation au fil du temps", "Attrait des normes"], "Landmark designation?": ["Non"], "Afficher seulement les \u00e9tudes de cas des programmes qui font l'objet d'une diffusion g\u00e9n\u00e9rale": ["Non"]}, "112": {"Sujet": ["Environnement:", "Environnement: Changements climatiques \u2013 att\u00e9nuation", "Environnement: L\u2019\u00e9cotransport", "Promotion de la sant\u00e9: Vie active"], "Resource type": ["Case Study"], "Endroit": ["Canada", "Canada-Ontario"], "Outils de changement utilis\u00e9s": ["M\u00e9dias", "Soutenir la motivation au fil du temps", "Attrait des normes"], "Landmark designation?": ["Non"], "Afficher seulement les \u00e9tudes de cas des programmes qui font l'objet d'une diffusion g\u00e9n\u00e9rale": ["Non"]}, "115": {"Sujet": ["Environnement:", "Environnement: Changements climatiques \u2013 att\u00e9nuation", "Environnement: L\u2019\u00e9cotransport", "Promotion de la sant\u00e9", "Promotion de la sant\u00e9: Vie active", "Promotion de la sant\u00e9: Conditions du milieu", "S\u00e9curit\u00e9", "S\u00e9curit\u00e9: S\u00e9curit\u00e9 routi\u00e8re "], "Resource type": ["Case Study"], "Endroit": ["Canada", "Canada-Alberta", "Canada-British Columbia", "Canada-Manitoba", "Canada-Nouvelle-\u00c9cosse", "Canada-Ontario", "Canada-IPE", "Canada-Quebec"], "Outils de changement utilis\u00e9s": ["Soutenir la motivation au fil du temps", "Attrait des normes"], "Landmark designation?": ["Oui"], "Afficher seulement les \u00e9tudes de cas des programmes qui font l'objet d'une diffusion g\u00e9n\u00e9rale": ["Oui"]}, "117": {"Sujet": ["Environnement:", "Environnement: Changements climatiques \u2013 att\u00e9nuation", "Environnement: Efficacit\u00e9 \u00e9nerg\u00e9tique", "Environnement: L\u2019\u00e9cotransport", "Promotion de la sant\u00e9", "Promotion de la sant\u00e9: Vie active", "Promotion de la sant\u00e9: Conditions du milieu"], "Resource type": ["Case Study"], "Endroit": ["\u00c9tats-Unis", "EU-California"], "Outils de changement utilis\u00e9s": ["M\u00e9dias", "Communications personnalis\u00e9es percutantes", "Attrait des normes"], "Landmark designation?": ["Non"], "Afficher seulement les \u00e9tudes de cas des programmes qui font l'objet d'une diffusion g\u00e9n\u00e9rale": ["Non"]}, "118": {"Sujet": ["Environnement:", "Environnement: D\u00e9chets", "Environnement: D\u00e9chets: D\u00e9chets domestiques dangereux", "Environnement: D\u00e9chets: Recyclage", "Environnement: D\u00e9chets: R\u00e9duction"], "Resource type": ["Case Study"], "Endroit": ["Canada", "Canada-Nouvelle-\u00c9cosse"], "Outils de changement utilis\u00e9s": ["M\u00e9dias", "Communications personnalis\u00e9es percutantes", "Soutenir la motivation au fil du temps"], "Landmark designation?": ["Non"], "Afficher seulement les \u00e9tudes de cas des programmes qui font l'objet d'une diffusion g\u00e9n\u00e9rale": ["Non"]}, "128": {"Sujet": ["Environnement:", "Environnement: Pr\u00e9vention de la pollution", "Environnement: Am\u00e9nagement paysager", "Promotion de la sant\u00e9", "Promotion de la sant\u00e9: Conditions du milieu"], "Resource type": ["Case Study"], "Endroit": ["\u00c9tats-Unis", "EU-Washington"], "Outils de changement utilis\u00e9s": ["M\u00e9dias", "Attrait des normes"], "Landmark designation?": ["Non"], "Afficher seulement les \u00e9tudes de cas des programmes qui font l'objet d'une diffusion g\u00e9n\u00e9rale": ["Non"]}, "136": {"Sujet": ["Environnement:", "Environnement: Pr\u00e9vention de la pollution", "Environnement: Am\u00e9nagement paysager", "Promotion de la sant\u00e9", "Promotion de la sant\u00e9: Conditions du milieu"], "Resource type": ["Case Study"], "Endroit": ["Canada", "Canada-Ontario"], "Outils de changement utilis\u00e9s": ["M\u00e9dias", "Communications personnalis\u00e9es percutantes", "Soutenir la motivation au fil du temps", "Attrait des normes"], "Landmark designation?": ["Non"], "Afficher seulement les \u00e9tudes de cas des programmes qui font l'objet d'une diffusion g\u00e9n\u00e9rale": ["Oui"]}, "137": {"Sujet": ["Environnement:", "Environnement: Pr\u00e9vention de la pollution", "Promotion de la sant\u00e9", "Promotion de la sant\u00e9: Conditions du milieu", "Promotion de la sant\u00e9: Milieux ferm\u00e9s (qualit\u00e9 de l\u2019air \u00e0 l\u2019int\u00e9rieur)", "S\u00e9curit\u00e9", "S\u00e9curit\u00e9: Sant\u00e9 et s\u00e9curit\u00e9 au travail"], "Resource type": ["Case Study"], "Endroit": ["Canada", "Canada-Manitoba"], "Outils de changement utilis\u00e9s": ["M\u00e9dias", "Soutenir la motivation au fil du temps"], "Landmark designation?": ["Non"], "Afficher seulement les \u00e9tudes de cas des programmes qui font l'objet d'une diffusion g\u00e9n\u00e9rale": ["Non"]}, "447": {"Sujet": ["Environnement:", "Environnement: L\u2019\u00e9cotransport"], "Resource type": ["Case Study"], "Endroit": ["Canada", "Canada-Alberta"], "Outils de changement utilis\u00e9s": ["Soutenir la motivation au fil du temps"], "Landmark designation?": ["Oui"], "Afficher seulement les \u00e9tudes de cas des programmes qui font l'objet d'une diffusion g\u00e9n\u00e9rale": ["Non"]}, "445": {"Sujet": ["Environnement:", "Environnement: Valorisation de l'eau"], "Resource type": ["Case Study"], "Endroit": ["Canada", "Canada-Ontario"], "Outils de changement utilis\u00e9s": ["M\u00e9dias", "Communications personnalis\u00e9es percutantes", "Soutenir la motivation au fil du temps"]}, "3": {"Sujet": ["Environnement:", "Environnement: Changements climatiques \u2013 att\u00e9nuation", "Environnement: Efficacit\u00e9 \u00e9nerg\u00e9tique", "Environnement: Valorisation de l'eau"], "Resource type": ["Case Study"], "Endroit": ["Canada", "Canada-British Columbia"], "Outils de changement utilis\u00e9s": ["M\u00e9dias"], "Landmark designation?": ["Non"], "Afficher seulement les \u00e9tudes de cas des programmes qui font l'objet d'une diffusion g\u00e9n\u00e9rale": ["Non"]}, "4": {"Sujet": ["Environnement:", "Environnement: Changements climatiques - adaptation", "Environnement: Valorisation de l'eau"], "Resource type": ["Case Study"], "Endroit": ["Canada", "Canada-Nouvelle-\u00c9cosse"], "Outils de changement utilis\u00e9s": ["Soutenir la motivation au fil du temps", "Attrait des normes"], "Landmark designation?": ["Non"], "Afficher seulement les \u00e9tudes de cas des programmes qui font l'objet d'une diffusion g\u00e9n\u00e9rale": ["Non"]}, "5": {"Sujet": ["Environnement:", "Environnement: Air pur", "Environnement: Changements climatiques \u2013 att\u00e9nuation", "Environnement: L\u2019\u00e9cotransport", "Promotion de la sant\u00e9", "Promotion de la sant\u00e9: Vie active", "Promotion de la sant\u00e9: Sant\u00e9 cardiovasculaire"], "Resource type": ["Case Study"], "Endroit": ["Canada", "Canada-British Columbia"], "Landmark designation?": ["Non"], "Afficher seulement les \u00e9tudes de cas des programmes qui font l'objet d'une diffusion g\u00e9n\u00e9rale": ["Oui"]}, "13": {"Sujet": ["Environnement:", "Environnement: D\u00e9chets: R\u00e9utillisation"], "Resource type": ["Case Study"], "Endroit": ["Canada", "Canada-Alberta"], "Outils de changement utilis\u00e9s": ["M\u00e9dias"], "Landmark designation?": ["Non"], "Afficher seulement les \u00e9tudes de cas des programmes qui font l'objet d'une diffusion g\u00e9n\u00e9rale": ["Non"]}, "7": {"Sujet": ["Environnement:", "Environnement: Changements climatiques \u2013 att\u00e9nuation", "Environnement: L\u2019\u00e9cotransport", "Promotion de la sant\u00e9", "Promotion de la sant\u00e9: Vie active", "Promotion de la sant\u00e9: Conditions du milieu", "Promotion de la sant\u00e9: Sant\u00e9 cardiovasculaire"], "Resource type": ["Case Study"], "Endroit": ["Canada", "Canada-Ontario"], "Outils de changement utilis\u00e9s": ["Communications personnalis\u00e9es percutantes", "Soutenir la motivation au fil du temps", "Attrait des normes"], "Landmark designation?": ["Non"], "Afficher seulement les \u00e9tudes de cas des programmes qui font l'objet d'une diffusion g\u00e9n\u00e9rale": ["Non"]}, "9": {"Sujet": ["Environnement:", "Environnement: Changements climatiques \u2013 att\u00e9nuation", "Environnement: Efficacit\u00e9 \u00e9nerg\u00e9tique", "Environnement: Milieux ferm\u00e9s (qualit\u00e9 de l\u2019air \u00e0 l\u2019int\u00e9rieur)", "Environnement: Pr\u00e9vention de la pollution", "Environnement: Am\u00e9nagement paysager", "Environnement: D\u00e9chets", "Environnement: D\u00e9chets: D\u00e9chets domestiques dangereux", "Environnement: Valorisation de l'eau", "Promotion de la sant\u00e9", "Promotion de la sant\u00e9: Vie active", "Promotion de la sant\u00e9: Conditions du milieu", "Promotion de la sant\u00e9: Milieux ferm\u00e9s (qualit\u00e9 de l\u2019air \u00e0 l\u2019int\u00e9rieur)"], "Resource type": ["Case Study"], "Endroit": ["Canada", "Canada-Ontario"], "Outils de changement utilis\u00e9s": ["M\u00e9dias"], "Landmark designation?": ["Non"], "Afficher seulement les \u00e9tudes de cas des programmes qui font l'objet d'une diffusion g\u00e9n\u00e9rale": ["Non"]}, "10": {"Sujet": ["Environnement:", "Environnement: D\u00e9chets", "Environnement: D\u00e9chets: Recyclage"], "Resource type": ["Case Study"], "Endroit": ["\u00c9tats-Unis", "EU-Washington"], "Outils de changement utilis\u00e9s": ["M\u00e9dias"], "Landmark designation?": ["Non"], "Afficher seulement les \u00e9tudes de cas des programmes qui font l'objet d'une diffusion g\u00e9n\u00e9rale": ["Non"]}, "12": {"Sujet": ["Environnement:", "Environnement: Air pur", "Environnement: Changements climatiques \u2013 att\u00e9nuation", "Environnement: L\u2019\u00e9cotransport", "Promotion de la sant\u00e9", "Promotion de la sant\u00e9: Vie active", "Promotion de la sant\u00e9: Sant\u00e9 cardiovasculaire"], "Resource type": ["Case Study"], "Endroit": ["\u00c9tats-Unis", "EU-Colorado"], "Outils de changement utilis\u00e9s": ["Communications personnalis\u00e9es percutantes", "Attrait des normes"], "Landmark designation?": ["Non"], "Afficher seulement les \u00e9tudes de cas des programmes qui font l'objet d'une diffusion g\u00e9n\u00e9rale": ["Non"]}, "14": {"Sujet": ["Environnement:", "Environnement: Changements climatiques \u2013 att\u00e9nuation", "Environnement: Efficacit\u00e9 \u00e9nerg\u00e9tique", "Environnement: Am\u00e9nagement paysager"], "Resource type": ["Case Study"], "Endroit": ["Canada", "Canada-Ontario"], "Outils de changement utilis\u00e9s": ["Communications personnalis\u00e9es percutantes", "Soutenir la motivation au fil du temps", "Attrait des normes"], "Landmark designation?": ["Non"], "Afficher seulement les \u00e9tudes de cas des programmes qui font l'objet d'une diffusion g\u00e9n\u00e9rale": ["Non"]}, "15": {"Sujet": ["Environnement:", "Environnement: Changements climatiques \u2013 att\u00e9nuation", "Environnement: Efficacit\u00e9 \u00e9nerg\u00e9tique"], "Resource type": ["Case Study"], "Endroit": ["\u00c9tats-Unis"], "Outils de changement utilis\u00e9s": ["Communications personnalis\u00e9es percutantes", "Soutenir la motivation au fil du temps"], "Landmark designation?": ["Non"], "Afficher seulement les \u00e9tudes de cas des programmes qui font l'objet d'une diffusion g\u00e9n\u00e9rale": ["Oui"]}, "16": {"Sujet": ["Environnement:", "Environnement: Changements climatiques \u2013 att\u00e9nuation", "Environnement: Efficacit\u00e9 \u00e9nerg\u00e9tique"], "Resource type": ["Case Study"], "Endroit": ["\u00c9tats-Unis", "EU-Iowa"], "Landmark designation?": ["Non"], "Afficher seulement les \u00e9tudes de cas des programmes qui font l'objet d'une diffusion g\u00e9n\u00e9rale": ["Non"]}, "18": {"Sujet": ["Environnement:", "Environnement: D\u00e9chets", "Environnement: D\u00e9chets: Recyclage", "Environnement: D\u00e9chets: R\u00e9duction"], "Resource type": ["Case Study"], "Endroit": ["Canada", "Canada-Ontario"], "Outils de changement utilis\u00e9s": ["Attrait des normes"], "Landmark designation?": ["Non"], "Afficher seulement les \u00e9tudes de cas des programmes qui font l'objet d'une diffusion g\u00e9n\u00e9rale": ["Non"]}, "26": {"Sujet": ["Environnement:", "Environnement: Milieux ferm\u00e9s (qualit\u00e9 de l\u2019air \u00e0 l\u2019int\u00e9rieur)", "Environnement: Pr\u00e9vention de la pollution", "Environnement: D\u00e9chets", "Environnement: D\u00e9chets: D\u00e9chets domestiques dangereux", "Promotion de la sant\u00e9", "Promotion de la sant\u00e9: Conditions du milieu", "Promotion de la sant\u00e9: Milieux ferm\u00e9s (qualit\u00e9 de l\u2019air \u00e0 l\u2019int\u00e9rieur)"], "Resource type": ["Case Study"], "Endroit": ["Canada", "Canada-Ontario"], "Outils de changement utilis\u00e9s": ["Soutenir la motivation au fil du temps", "Attrait des normes"], "Landmark designation?": ["Non"], "Afficher seulement les \u00e9tudes de cas des programmes qui font l'objet d'une diffusion g\u00e9n\u00e9rale": ["Non"]}, "17": {"Sujet": ["Environnement:", "Environnement: Changements climatiques \u2013 att\u00e9nuation", "Environnement: Efficacit\u00e9 \u00e9nerg\u00e9tique"], "Resource type": ["Case Study"], "Endroit": ["Canada", "Canada-Alberta"], "Outils de changement utilis\u00e9s": ["M\u00e9dias", "Attrait des normes"], "Landmark designation?": ["Non"], "Afficher seulement les \u00e9tudes de cas des programmes qui font l'objet d'une diffusion g\u00e9n\u00e9rale": ["Non"]}, "19": {"Sujet": ["Environnement:", "Environnement: Changements climatiques \u2013 att\u00e9nuation", "Environnement: Efficacit\u00e9 \u00e9nerg\u00e9tique"], "Resource type": ["Case Study"], "Endroit": ["\u00c9tats-Unis", "EU-California"], "Outils de changement utilis\u00e9s": ["Communications personnalis\u00e9es percutantes", "Soutenir la motivation au fil du temps", "Attrait des normes"], "Landmark designation?": ["Non"], "Afficher seulement les \u00e9tudes de cas des programmes qui font l'objet d'une diffusion g\u00e9n\u00e9rale": ["Non"]}, "27": {"Sujet": ["Environnement:", "Environnement: D\u00e9chets", "Environnement: D\u00e9chets: Recyclage"], "Resource type": ["Case Study"], "Endroit": ["Canada", "Canada-Ontario"], "Landmark designation?": ["Non"], "Afficher seulement les \u00e9tudes de cas des programmes qui font l'objet d'une diffusion g\u00e9n\u00e9rale": ["Non"]}, "20": {"Sujet": ["Environnement:", "Environnement: Changements climatiques \u2013 att\u00e9nuation", "Environnement: Efficacit\u00e9 \u00e9nerg\u00e9tique", "Environnement: Pr\u00e9vention de la pollution", "Environnement: Am\u00e9nagement paysager", "Environnement: Valorisation de l'eau"], "Resource type": ["Case Study"], "Endroit": ["Canada", "Canada-Ontario"], "Outils de changement utilis\u00e9s": ["M\u00e9dias", "Communications personnalis\u00e9es percutantes"], "Landmark designation?": ["Non"], "Afficher seulement les \u00e9tudes de cas des programmes qui font l'objet d'une diffusion g\u00e9n\u00e9rale": ["Non"]}, "23": {"Sujet": ["Environnement:", "Environnement: D\u00e9chets", "Environnement: D\u00e9chets: Compostage", "Environnement: D\u00e9chets: Recyclage"], "Resource type": ["Case Study"], "Endroit": ["Canada", "Canada-Alberta"], "Outils de changement utilis\u00e9s": ["Communications personnalis\u00e9es percutantes"], "Landmark designation?": ["Non"], "Afficher seulement les \u00e9tudes de cas des programmes qui font l'objet d'une diffusion g\u00e9n\u00e9rale": ["Non"]}, "34": {"Sujet": ["Environnement:", "Promotion de la sant\u00e9", "Promotion de la sant\u00e9: Vie active", "Promotion de la sant\u00e9: Sant\u00e9 cardiovasculaire"], "Resource type": ["Case Study"], "Endroit": ["Canada", "EU-Washington"], "Outils de changement utilis\u00e9s": ["Communications personnalis\u00e9es percutantes"], "Landmark designation?": ["Non"], "Afficher seulement les \u00e9tudes de cas des programmes qui font l'objet d'une diffusion g\u00e9n\u00e9rale": ["Non"]}, "24": {"Sujet": ["Environnement:", "Environnement: Milieux ferm\u00e9s (qualit\u00e9 de l\u2019air \u00e0 l\u2019int\u00e9rieur)", "Environnement: Pr\u00e9vention de la pollution", "Environnement: D\u00e9chets", "Environnement: D\u00e9chets: D\u00e9chets domestiques dangereux", "Promotion de la sant\u00e9", "Promotion de la sant\u00e9: Conditions du milieu", "Promotion de la sant\u00e9: Milieux ferm\u00e9s (qualit\u00e9 de l\u2019air \u00e0 l\u2019int\u00e9rieur)"], "Resource type": ["Case Study"], "Endroit": ["Canada", "Canada-Ontario"], "Outils de changement utilis\u00e9s": ["Communications personnalis\u00e9es percutantes"], "Landmark designation?": ["Non"], "Afficher seulement les \u00e9tudes de cas des programmes qui font l'objet d'une diffusion g\u00e9n\u00e9rale": ["Non"]}, "451": {"Sujet": ["Environnement:", "Environnement: Air pur", "Environnement: Changements climatiques \u2013 att\u00e9nuation", "Environnement: Efficacit\u00e9 \u00e9nerg\u00e9tique", "Environnement: Pr\u00e9vention de la pollution", "Promotion de la sant\u00e9", "Promotion de la sant\u00e9: Conditions du milieu"], "Resource type": ["Case Study"], "Endroit": ["Allemagne"], "Outils de changement utilis\u00e9s": ["Attrait des normes"], "Landmark designation?": ["Oui"], "Afficher seulement les \u00e9tudes de cas des programmes qui font l'objet d'une diffusion g\u00e9n\u00e9rale": ["Non"]}, "452": {"Sujet": ["Environnement:", "Environnement: Changements climatiques \u2013 att\u00e9nuation", "Environnement: Efficacit\u00e9 \u00e9nerg\u00e9tique"], "Resource type": ["Case Study"], "Endroit": ["Allemagne"], "Outils de changement utilis\u00e9s": ["M\u00e9dias", "Soutenir la motivation au fil du temps", "Attrait des normes"], "Landmark designation?": ["Oui"], "Afficher seulement les \u00e9tudes de cas des programmes qui font l'objet d'une diffusion g\u00e9n\u00e9rale": ["Non"]}, "35": {"Sujet": ["Environnement:", "Environnement: Air pur", "Environnement: Changements climatiques \u2013 att\u00e9nuation", "Environnement: Pr\u00e9vention de la pollution", "Environnement: L\u2019\u00e9cotransport"], "Resource type": ["Case Study"], "Endroit": ["Canada", "Canada-Alberta", "Canada-Nouvelle-\u00c9cosse", "Canada-Quebec", "Norv\u00e8ge", "Panama", "EU-California", "EU-Colorado", "EU-DC", "EU-Floride", "EU-Iowa", "EU-Ohio", "EU-Vermont"], "Outils de changement utilis\u00e9s": ["M\u00e9dias", "Soutenir la motivation au fil du temps"], "Landmark designation?": ["Non"], "Afficher seulement les \u00e9tudes de cas des programmes qui font l'objet d'une diffusion g\u00e9n\u00e9rale": ["Non"]}, "72": {"Sujet": ["Environnement:", "Environnement: Changements climatiques \u2013 att\u00e9nuation", "Environnement: Efficacit\u00e9 \u00e9nerg\u00e9tique"], "Resource type": ["Case Study"], "Endroit": ["\u00c9tats-Unis"], "Outils de changement utilis\u00e9s": ["M\u00e9dias", "Communications personnalis\u00e9es percutantes"], "Landmark designation?": ["Non"], "Afficher seulement les \u00e9tudes de cas des programmes qui font l'objet d'une diffusion g\u00e9n\u00e9rale": ["Non"]}, "453": {"Sujet": ["Environnement:", "Environnement: Air pur", "Environnement: Changements climatiques \u2013 att\u00e9nuation", "Environnement: Pr\u00e9vention de la pollution", "Environnement: L\u2019\u00e9cotransport", "Promotion de la sant\u00e9", "Promotion de la sant\u00e9: Vie active", "Promotion de la sant\u00e9: Conditions du milieu", "Promotion de la sant\u00e9: Sant\u00e9 cardiovasculaire", "S\u00e9curit\u00e9", "S\u00e9curit\u00e9: S\u00e9curit\u00e9 routi\u00e8re "], "Resource type": ["Case Study"], "Endroit": ["France"], "Outils de changement utilis\u00e9s": ["M\u00e9dias", "Soutenir la motivation au fil du temps", "Attrait des normes"], "Landmark designation?": ["Oui"], "Afficher seulement les \u00e9tudes de cas des programmes qui font l'objet d'une diffusion g\u00e9n\u00e9rale": ["Non"]}, "92": {"Sujet": ["Environnement:", "Environnement: Changements climatiques \u2013 att\u00e9nuation", "Environnement: L\u2019\u00e9cotransport", "Promotion de la sant\u00e9", "Promotion de la sant\u00e9: Vie active", "Promotion de la sant\u00e9: Conditions du milieu", "Promotion de la sant\u00e9: Sant\u00e9 cardiovasculaire"], "Resource type": ["Case Study"], "Endroit": ["Canada", "Canada-British Columbia"], "Outils de changement utilis\u00e9s": ["Communications personnalis\u00e9es percutantes"], "Landmark designation?": ["Non"], "Afficher seulement les \u00e9tudes de cas des programmes qui font l'objet d'une diffusion g\u00e9n\u00e9rale": ["Non"]}, "454": {"Sujet": ["Environnement:", "Environnement: Air pur", "Environnement: Changements climatiques \u2013 att\u00e9nuation", "Environnement: Pr\u00e9vention de la pollution", "Environnement: L\u2019\u00e9cotransport", "Promotion de la sant\u00e9", "Promotion de la sant\u00e9: Vie active", "Promotion de la sant\u00e9: Conditions du milieu", "Promotion de la sant\u00e9: Sant\u00e9 cardiovasculaire", "S\u00e9curit\u00e9", "S\u00e9curit\u00e9: S\u00e9curit\u00e9 routi\u00e8re "], "Resource type": ["Case Study"], "Endroit": ["Danemark"], "Outils de changement utilis\u00e9s": ["M\u00e9dias", "Soutenir la motivation au fil du temps", "Attrait des normes"], "Landmark designation?": ["Oui"], "Afficher seulement les \u00e9tudes de cas des programmes qui font l'objet d'une diffusion g\u00e9n\u00e9rale": ["Non"]}, "106": {"Sujet": ["Environnement:", "Environnement: Changements climatiques \u2013 att\u00e9nuation", "Environnement: Efficacit\u00e9 \u00e9nerg\u00e9tique"], "Resource type": ["Case Study"], "Endroit": ["\u00c9tats-Unis", "EU-California"], "Outils de changement utilis\u00e9s": ["M\u00e9dias", "Soutenir la motivation au fil du temps"], "Landmark designation?": ["Non"], "Afficher seulement les \u00e9tudes de cas des programmes qui font l'objet d'une diffusion g\u00e9n\u00e9rale": ["Non"]}, "107": {"Sujet": ["Environnement:", "Environnement: Changements climatiques \u2013 att\u00e9nuation", "Environnement: L\u2019\u00e9cotransport"], "Resource type": ["Case Study"], "Outils de changement utilis\u00e9s": ["M\u00e9dias", "Communications personnalis\u00e9es percutantes", "Soutenir la motivation au fil du temps", "Attrait des normes"], "Landmark designation?": ["Non"], "Afficher seulement les \u00e9tudes de cas des programmes qui font l'objet d'une diffusion g\u00e9n\u00e9rale": ["Non"]}, "108": {"Sujet": ["Environnement:", "Environnement: Changements climatiques \u2013 att\u00e9nuation", "Environnement: Valorisation de l'eau"], "Resource type": ["Case Study"], "Endroit": ["Canada", "Canada-Ontario"], "Outils de changement utilis\u00e9s": ["M\u00e9dias", "Soutenir la motivation au fil du temps"], "Landmark designation?": ["Non"], "Afficher seulement les \u00e9tudes de cas des programmes qui font l'objet d'une diffusion g\u00e9n\u00e9rale": ["Non"]}, "109": {"Sujet": ["Environnement:", "Environnement: Changements climatiques \u2013 att\u00e9nuation", "Environnement: L\u2019\u00e9cotransport", "S\u00e9curit\u00e9", "S\u00e9curit\u00e9: S\u00e9curit\u00e9 routi\u00e8re "], "Resource type": ["Case Study"], "Endroit": ["Canada", "Canada-Alberta", "Canada-British Columbia", "Canada-Manitoba", "Canada-Nouvelle-\u00c9cosse", "Canada-Ontario", "Canada-IPE", "Canada-Quebec"], "Outils de changement utilis\u00e9s": ["Communications personnalis\u00e9es percutantes"], "Landmark designation?": ["Non"], "Afficher seulement les \u00e9tudes de cas des programmes qui font l'objet d'une diffusion g\u00e9n\u00e9rale": ["Oui"]}, "116": {"Sujet": ["Environnement:", "Environnement: Changements climatiques \u2013 att\u00e9nuation", "Environnement: L\u2019\u00e9cotransport", "Promotion de la sant\u00e9", "Promotion de la sant\u00e9: Vie active", "Promotion de la sant\u00e9: Sant\u00e9 cardiovasculaire", "S\u00e9curit\u00e9", "S\u00e9curit\u00e9: S\u00e9curit\u00e9 routi\u00e8re "], "Resource type": ["Case Study"], "Endroit": ["Canada", "Canada-British Columbia"], "Outils de changement utilis\u00e9s": ["M\u00e9dias", "Soutenir la motivation au fil du temps"], "Landmark designation?": ["Non"], "Afficher seulement les \u00e9tudes de cas des programmes qui font l'objet d'une diffusion g\u00e9n\u00e9rale": ["Non"]}, "135": {"Sujet": ["Environnement:", "Environnement: Changements climatiques \u2013 att\u00e9nuation", "Environnement: Pr\u00e9vention de la pollution", "Environnement: L\u2019\u00e9cotransport", "Promotion de la sant\u00e9", "Promotion de la sant\u00e9: Conditions du milieu"], "Resource type": ["Case Study"], "Endroit": ["Canada-Quebec"], "Outils de changement utilis\u00e9s": ["M\u00e9dias", "Communications personnalis\u00e9es percutantes", "Soutenir la motivation au fil du temps"], "Landmark designation?": ["Non"], "Afficher seulement les \u00e9tudes de cas des programmes qui font l'objet d'une diffusion g\u00e9n\u00e9rale": ["Non"]}, "441": {"Sujet": ["Environnement:", "Environnement: Milieux ferm\u00e9s (qualit\u00e9 de l\u2019air \u00e0 l\u2019int\u00e9rieur)", "Environnement: Pr\u00e9vention de la pollution", "Promotion de la sant\u00e9", "Promotion de la sant\u00e9: Conditions du milieu", "Promotion de la sant\u00e9: Milieux ferm\u00e9s (qualit\u00e9 de l\u2019air \u00e0 l\u2019int\u00e9rieur)"], "Resource type": ["Case Study"], "Endroit": ["Canada", "Canada-Ontario"], "Outils de changement utilis\u00e9s": ["Soutenir la motivation au fil du temps"], "Landmark designation?": ["Non"], "Afficher seulement les \u00e9tudes de cas des programmes qui font l'objet d'une diffusion g\u00e9n\u00e9rale": ["Non"]}, "455": {"Sujet": ["Environnement:", "Environnement: Changements climatiques \u2013 att\u00e9nuation", "Environnement: L\u2019\u00e9cotransport"], "Resource type": ["Case Study"], "Endroit": ["\u00c9tats-Unis", "EU-Texas"], "Landmark designation?": ["Non"], "Afficher seulement les \u00e9tudes de cas des programmes qui font l'objet d'une diffusion g\u00e9n\u00e9rale": ["Non"]}, "456": {"Sujet": ["Environnement:", "Environnement: Air pur", "Environnement: Changements climatiques \u2013 att\u00e9nuation", "Environnement: L\u2019\u00e9cotransport"], "Resource type": ["Case Study"], "Endroit": ["\u00c9tats-Unis", "EU-California"], "Landmark designation?": ["Non"], "Afficher seulement les \u00e9tudes de cas des programmes qui font l'objet d'une diffusion g\u00e9n\u00e9rale": ["Non"]}, "457": {"Sujet": ["Environnement:", "Environnement: Changements climatiques \u2013 att\u00e9nuation", "Environnement: Efficacit\u00e9 \u00e9nerg\u00e9tique"], "Resource type": ["Case Study"], "Endroit": ["\u00c9tats-Unis", "EU-Illinois"], "Outils de changement utilis\u00e9s": ["Soutenir la motivation au fil du temps", "Attrait des normes"], "Landmark designation?": ["Oui"], "Afficher seulement les \u00e9tudes de cas des programmes qui font l'objet d'une diffusion g\u00e9n\u00e9rale": ["Non"]}, "458": {"Sujet": ["Environnement:", "Environnement: Changements climatiques \u2013 att\u00e9nuation", "Environnement: D\u00e9chets", "Environnement: D\u00e9chets: R\u00e9duction", "Promotion de la sant\u00e9"], "Resource type": ["Case Study"], "Endroit": ["Autriche", "Canada", "France", "Allemagne", "\u00c9tats-Unis"], "Landmark designation?": ["Non"], "Afficher seulement les \u00e9tudes de cas des programmes qui font l'objet d'une diffusion g\u00e9n\u00e9rale": ["Oui"]}, "459": {"Sujet": ["Environnement:", "Environnement: Changements climatiques - adaptation", "Environnement: Changements climatiques \u2013 att\u00e9nuation", "Environnement: Valorisation de l'eau"], "Resource type": ["Case Study"], "Landmark designation?": ["Oui"], "Afficher seulement les \u00e9tudes de cas des programmes qui font l'objet d'une diffusion g\u00e9n\u00e9rale": ["Non"]}, "462": {"Sujet": ["Environnement:", "Environnement: D\u00e9chets", "Environnement: D\u00e9chets: R\u00e9utillisation", "Promotion de la sant\u00e9", "Promotion de la sant\u00e9: Nutrition"], "Resource type": ["Case Study"], "Outils de changement utilis\u00e9s": ["M\u00e9dias", "Attrait des normes"], "Landmark designation?": ["Non"], "Afficher seulement les \u00e9tudes de cas des programmes qui font l'objet d'une diffusion g\u00e9n\u00e9rale": ["Non"]}, "463": {"Sujet": ["Environnement:", "Environnement: Agriculture durable et conservation de la faune", "Promotion de la sant\u00e9", "Promotion de la sant\u00e9: Nutrition"], "Resource type": ["Case Study"], "Outils de changement utilis\u00e9s": ["Attrait des normes"], "Landmark designation?": ["Non"], "Afficher seulement les \u00e9tudes de cas des programmes qui font l'objet d'une diffusion g\u00e9n\u00e9rale": ["Non"]}, "476": {"Sujet": ["Environnement:", "Environnement: Valorisation de l'eau"], "Resource type": ["Case Study"], "Outils de changement utilis\u00e9s": ["M\u00e9dias", "Soutenir la motivation au fil du temps"], "Landmark designation?": ["Oui"], "Afficher seulement les \u00e9tudes de cas des programmes qui font l'objet d'une diffusion g\u00e9n\u00e9rale": ["Non"]}, "8": {"Sujet": ["Environnement:", "Environnement: D\u00e9chets"], "Resource type": ["Case Study"], "Endroit": ["Canada", "Canada-Ontario"], "Outils de changement utilis\u00e9s": ["M\u00e9dias", "Attrait des normes"], "Landmark designation?": ["Non"], "Afficher seulement les \u00e9tudes de cas des programmes qui font l'objet d'une diffusion g\u00e9n\u00e9rale": ["Non"]}, "81": {"Sujet": ["Environnement:", "Environnement: Changements climatiques \u2013 att\u00e9nuation", "Environnement: Efficacit\u00e9 \u00e9nerg\u00e9tique", "Environnement: Valorisation de l'eau"], "Resource type": ["Case Study"], "Endroit": ["Canada", "Canada-Ontario"], "Outils de changement utilis\u00e9s": ["M\u00e9dias", "Communications personnalis\u00e9es percutantes", "Soutenir la motivation au fil du temps"], "Landmark designation?": ["Non"], "Afficher seulement les \u00e9tudes de cas des programmes qui font l'objet d'une diffusion g\u00e9n\u00e9rale": ["Non"]}, "6": {"Sujet": ["Environnement:", "Environnement: D\u00e9chets", "Environnement: D\u00e9chets: Recyclage"], "Resource type": ["Case Study"], "Endroit": ["\u00c9tats-Unis", "EU-California"], "Outils de changement utilis\u00e9s": ["Communications personnalis\u00e9es percutantes", "Soutenir la motivation au fil du temps", "Attrait des normes"], "Landmark designation?": ["Non"], "Afficher seulement les \u00e9tudes de cas des programmes qui font l'objet d'une diffusion g\u00e9n\u00e9rale": ["Non"]}, "28": {"Sujet": ["Environnement:", "Environnement: D\u00e9chets", "Environnement: D\u00e9chets: Recyclage", "Environnement: D\u00e9chets: R\u00e9duction"], "Resource type": ["Case Study"], "Endroit": ["Canada", "Canada-Ontario"], "Landmark designation?": ["Non"], "Afficher seulement les \u00e9tudes de cas des programmes qui font l'objet d'une diffusion g\u00e9n\u00e9rale": ["Non"]}, "460": {"Sujet": ["Environnement:", "Environnement: D\u00e9chets"], "Resource type": ["Case Study"], "Outils de changement utilis\u00e9s": ["Soutenir la motivation au fil du temps", "Attrait des normes"], "Landmark designation?": ["Oui"], "Afficher seulement les \u00e9tudes de cas des programmes qui font l'objet d'une diffusion g\u00e9n\u00e9rale": ["Non"]}, "139": {"Sujet": ["Environnement: Changements climatiques \u2013 att\u00e9nuation"], "Resource type": ["Case Study"], "Endroit": ["\u00c9tats-Unis", "EU-Oregon"], "Outils de changement utilis\u00e9s": ["M\u00e9dias", "Attrait des normes"], "Landmark designation?": ["Non"], "Afficher seulement les \u00e9tudes de cas des programmes qui font l'objet d'une diffusion g\u00e9n\u00e9rale": ["Non"]}, "33": {"Sujet": ["Environnement: Pr\u00e9vention de la pollution", "Promotion de la sant\u00e9", "Promotion de la sant\u00e9: Conditions du milieu"], "Resource type": ["Case Study"], "Endroit": ["Canada", "Canada-Quebec"], "Outils de changement utilis\u00e9s": ["Communications personnalis\u00e9es percutantes", "Soutenir la motivation au fil du temps", "Attrait des normes"], "Landmark designation?": ["Non"], "Afficher seulement les \u00e9tudes de cas des programmes qui font l'objet d'une diffusion g\u00e9n\u00e9rale": ["Oui"]}, "443": {"Sujet": ["Environnement: L\u2019\u00e9cotransport"], "Resource type": ["Case Study"], "Endroit": ["Canada", "Canada-Ontario"], "Outils de changement utilis\u00e9s": ["M\u00e9dias"], "Afficher seulement les \u00e9tudes de cas des programmes qui font l'objet d'une diffusion g\u00e9n\u00e9rale": ["Non"]}, "461": {"Sujet": ["Promotion de la sant\u00e9", "Promotion de la sant\u00e9: Nutrition"], "Resource type": ["Case Study"], "Endroit": ["Canada-Quebec"], "Landmark designation?": ["Non"], "Afficher seulement les \u00e9tudes de cas des programmes qui font l'objet d'une diffusion g\u00e9n\u00e9rale": ["Non"]}, "465": {"Sujet": ["Promotion de la sant\u00e9", "Promotion de la sant\u00e9: SIDA"], "Resource type": ["Case Study"], "Endroit": ["Australie"], "Outils de changement utilis\u00e9s": ["M\u00e9dias"], "Landmark designation?": ["Non"], "Afficher seulement les \u00e9tudes de cas des programmes qui font l'objet d'une diffusion g\u00e9n\u00e9rale": ["Non"]}, "468": {"Sujet": ["Promotion de la sant\u00e9", "Promotion de la sant\u00e9: Tabagisme"], "Resource type": ["Case Study"], "Endroit": ["Canada"], "Outils de changement utilis\u00e9s": ["M\u00e9dias", "Soutenir la motivation au fil du temps", "Attrait des normes"], "Landmark designation?": ["Non"], "Afficher seulement les \u00e9tudes de cas des programmes qui font l'objet d'une diffusion g\u00e9n\u00e9rale": ["Non"]}, "469": {"Sujet": ["Promotion de la sant\u00e9", "Promotion de la sant\u00e9: Tabagisme"], "Resource type": ["Case Study"], "Endroit": ["Canada"], "Landmark designation?": ["Non"], "Afficher seulement les \u00e9tudes de cas des programmes qui font l'objet d'une diffusion g\u00e9n\u00e9rale": ["Non"]}, "30": {"Sujet": ["Promotion de la sant\u00e9", "Promotion de la sant\u00e9: SIDA"], "Resource type": ["Case Study"], "Endroit": ["Canada", "Canada-Quebec"], "Outils de changement utilis\u00e9s": ["Communications personnalis\u00e9es percutantes", "Soutenir la motivation au fil du temps", "Attrait des normes"], "Landmark designation?": ["Non"], "Afficher seulement les \u00e9tudes de cas des programmes qui font l'objet d'une diffusion g\u00e9n\u00e9rale": ["Non"]}, "126": {"Sujet": ["Promotion de la sant\u00e9"], "Resource type": ["Case Study"], "Endroit": ["Canada", "Canada-Alberta", "Canada-British Columbia", "Canada-Manitoba", "Canada-Nouvelle-\u00c9cosse", "Canada-Ontario", "Canada-IPE", "Canada-Quebec"], "Outils de changement utilis\u00e9s": ["M\u00e9dias", "Communications personnalis\u00e9es percutantes"], "Landmark designation?": ["Non"]}, "466": {"Sujet": ["Promotion de la sant\u00e9", "Promotion de la sant\u00e9: SIDA"], "Resource type": ["Case Study"], "Outils de changement utilis\u00e9s": ["Attrait des normes"], "Landmark designation?": ["Non"], "Afficher seulement les \u00e9tudes de cas des programmes qui font l'objet d'une diffusion g\u00e9n\u00e9rale": ["Non"]}, "464": {"Sujet": ["Promotion de la sant\u00e9", "Promotion de la sant\u00e9: SIDA"], "Resource type": ["Case Study"], "Endroit": ["\u00c9tats-Unis"], "Outils de changement utilis\u00e9s": ["Soutenir la motivation au fil du temps", "Attrait des normes"], "Landmark designation?": ["Non"], "Afficher seulement les \u00e9tudes de cas des programmes qui font l'objet d'une diffusion g\u00e9n\u00e9rale": ["Non"]}, "467": {"Sujet": ["Promotion de la sant\u00e9: Tabagisme"], "Resource type": ["Case Study"], "Endroit": ["\u00c9tats-Unis"], "Landmark designation?": ["Non"], "Afficher seulement les \u00e9tudes de cas des programmes qui font l'objet d'une diffusion g\u00e9n\u00e9rale": ["Non"]}, "472": {"Sujet": ["S\u00e9curit\u00e9", "S\u00e9curit\u00e9:  Pr\u00e9vention du harc\u00e8lement et de la violence", "S\u00e9curit\u00e9: Pr\u00e9vention du crime"], "Resource type": ["Case Study"], "Endroit": ["Canada"], "Outils de changement utilis\u00e9s": ["Attrait des normes"], "Landmark designation?": ["Non"], "Afficher seulement les \u00e9tudes de cas des programmes qui font l'objet d'une diffusion g\u00e9n\u00e9rale": ["Non"]}, "473": {"Sujet": ["S\u00e9curit\u00e9", "S\u00e9curit\u00e9:  Pr\u00e9vention du harc\u00e8lement et de la violence", "S\u00e9curit\u00e9: Pr\u00e9vention du crime"], "Resource type": ["Case Study"], "Outils de changement utilis\u00e9s": ["Attrait des normes"], "Landmark designation?": ["Non"], "Afficher seulement les \u00e9tudes de cas des programmes qui font l'objet d'une diffusion g\u00e9n\u00e9rale": ["Non"]}, "474": {"Sujet": ["S\u00e9curit\u00e9", "S\u00e9curit\u00e9:  Pr\u00e9vention du harc\u00e8lement et de la violence"], "Resource type": ["Case Study"], "Endroit": ["Norv\u00e8ge"], "Outils de changement utilis\u00e9s": ["Soutenir la motivation au fil du temps", "Attrait des normes"], "Landmark designation?": ["Non"], "Afficher seulement les \u00e9tudes de cas des programmes qui font l'objet d'une diffusion g\u00e9n\u00e9rale": ["Non"]}, "471": {"Sujet": ["S\u00e9curit\u00e9", "S\u00e9curit\u00e9: Pr\u00e9vention du crime", "S\u00e9curit\u00e9: S\u00e9curit\u00e9 routi\u00e8re "], "Resource type": ["Case Study"], "Endroit": ["\u00c9tats-Unis"], "Landmark designation?": ["Non"], "Afficher seulement les \u00e9tudes de cas des programmes qui font l'objet d'une diffusion g\u00e9n\u00e9rale": ["Non"]}, "475": {"Sujet": ["S\u00e9curit\u00e9", "S\u00e9curit\u00e9:  Pr\u00e9vention du harc\u00e8lement et de la violence"], "Resource type": ["Case Study"], "Outils de changement utilis\u00e9s": ["M\u00e9dias", "Attrait des normes"], "Landmark designation?": ["Non"], "Afficher seulement les \u00e9tudes de cas des programmes qui font l'objet d'une diffusion g\u00e9n\u00e9rale": ["Non"]}, "470": {"Sujet": ["S\u00e9curit\u00e9: Pr\u00e9vention du crime"], "Resource type": ["Case Study"], "Outils de changement utilis\u00e9s": ["Attrait des normes"], "Landmark designation?": ["Non"], "Afficher seulement les \u00e9tudes de cas des programmes qui font l'objet d'une diffusion g\u00e9n\u00e9rale": ["Non"]}, "113": {"Outils de changement utilis\u00e9s": ["M\u00e9dias", "Soutenir la motivation au fil du temps", "Attrait des normes"], "Resource type": ["Case Study"], "Landmark designation?": ["Non"]}, "125": {"Outils de changement utilis\u00e9s": ["Soutenir la motivation au fil du temps"], "Resource type": ["Case Study"], "Landmark designation?": ["Non"], "Afficher seulement les \u00e9tudes de cas des programmes qui font l'objet d'une diffusion g\u00e9n\u00e9rale": ["Non"]}, "123": {"Landmark designation?": ["Non"], "Resource type": ["Case Study"], "Afficher seulement les \u00e9tudes de cas des programmes qui font l'objet d'une diffusion g\u00e9n\u00e9rale": ["Non"]}, "130": {"Landmark designation?": ["Non"], "Resource type": ["Case Study"], "Afficher seulement les \u00e9tudes de cas des programmes qui font l'objet d'une diffusion g\u00e9n\u00e9rale": ["Non"]}}